sklarpy/__init__.py
sklarpy/copulas/__init__.py
sklarpy/copulas/_fitted_dists.py
sklarpy/copulas/_prefit_dists.py
sklarpy/copulas/distributions.py
sklarpy/copulas/distributions_map.py
sklarpy/copulas/marginal_fitter.py
sklarpy/copulas/_distributions/__init__.py
sklarpy/copulas/_distributions/_archimedean.py
sklarpy/copulas/_distributions/_gaussian.py
sklarpy/copulas/_distributions/_gaussian_kde.py
sklarpy/copulas/_distributions/_generalized_hyperbolic.py
sklarpy/copulas/_distributions/_hyperbolics.py
sklarpy/copulas/_distributions/_skewed_t.py
sklarpy/copulas/_distributions/_student_t.py
sklarpy/copulas/_distributions/_symmetric_generalized_hyperbolic.py
sklarpy/copulas/_distributions/_symmetric_hyperbolics.py
sklarpy/misc/__init__.py
sklarpy/misc/correlation.py
sklarpy/misc/debye.py
sklarpy/misc/gradient.py
sklarpy/misc/modified_bessel.py
sklarpy/multivariate/__init__.py
sklarpy/multivariate/_fitted_dists.py
sklarpy/multivariate/_prefit_dists.py
sklarpy/multivariate/distributions.py
sklarpy/multivariate/distributions_map.py
sklarpy/multivariate/_distributions/__init__.py
sklarpy/multivariate/_distributions/_archimedean.py
sklarpy/multivariate/_distributions/_gaussian_kde.py
sklarpy/multivariate/_distributions/_generalized_hyperbolic.py
sklarpy/multivariate/_distributions/_hyperbolics.py
sklarpy/multivariate/_distributions/_normal.py
sklarpy/multivariate/_distributions/_skewed_t.py
sklarpy/multivariate/_distributions/_student_t.py
sklarpy/multivariate/_distributions/_symmetric_generalized_hyperbolic.py
sklarpy/multivariate/_distributions/_symmetric_hyperbolics.py
sklarpy/multivariate/_params/__init__.py
sklarpy/multivariate/_params/_archimedean.py
sklarpy/multivariate/_params/_gaussian_kde.py
sklarpy/multivariate/_params/_generalized_hyperbolic.py
sklarpy/multivariate/_params/_hyperbolics.py
sklarpy/multivariate/_params/_normal.py
sklarpy/multivariate/_params/_skewed_t.py
sklarpy/multivariate/_params/_student_t.py
sklarpy-1.0.0.dist-info/LICENSE
sklarpy-1.0.0.dist-info/METADATA
sklarpy-1.0.0.dist-info/WHEEL
sklarpy-1.0.0.dist-info/top_level.txt
sklarpy-1.0.0.dist-info/RECORD
