Metadata-Version: 2.1
Name: sklarpy
Version: 1.0.0
Summary: Copula, Multivariate and Univariate probability distribution fitting in Python.
Author-email: Tyler Mitchell <tylerfmitchell1999@gmail.com>
Maintainer-email: Tyler Mitchell <tylerfmitchell1999@gmail.com>
Project-URL: Homepage, https://github.com/tfm000/sklarpy
Project-URL: Bug Reports, https://github.com/tfm000/sklarpy/issues
Project-URL: Source, https://github.com/tfm000/sklarpy
Keywords: SklarPy,Sklar,Copula,Copulas,Copulae,Probability,Distribution,Univariate,Bivariate,Multivariate,Joint,CDF,PDF,Modeling,Quantitative,Fitting,SciPy,Statistics,Mathematics,Science,Scientific,Finance,Risk,VaR,Machine Learning,Variables
Classifier: Development Status :: 3 - Alpha
Classifier: Intended Audience :: Science/Research
Classifier: Intended Audience :: Financial and Insurance Industry
Classifier: Intended Audience :: Developers
Classifier: Intended Audience :: Education
Classifier: Topic :: Software Development :: Build Tools
Classifier: License :: OSI Approved :: MIT License
Classifier: Programming Language :: Python :: 3.9
Classifier: Programming Language :: Python :: 3.10
Classifier: Programming Language :: Python :: 3.11
Requires-Python: >=3.9
License-File: LICENSE
Requires-Dist: scipy >=1.11.0
Requires-Dist: numpy >=1.24.3
Requires-Dist: pandas >=2.0.2
Requires-Dist: matplotlib >=3.7.1
Requires-Dist: tqdm >=4.65.0
Requires-Dist: dill >=0.3.6
Requires-Dist: seaborn >=0.12.2
Provides-Extra: dev
Requires-Dist: pytest ==7.1.2 ; extra == 'dev'
Requires-Dist: tox ==3.25.1 ; extra == 'dev'
Provides-Extra: docs
Requires-Dist: sphinx ~=4.2.0 ; extra == 'docs'
